release_notes_generator/__init__.py
release_notes_generator/cli.py
release_notes_generator/release_note_generator.py
release_notes_generator/services.py
release_notes_generator-1.2.1.dist-info/LICENSE.txt
release_notes_generator-1.2.1.dist-info/METADATA
release_notes_generator-1.2.1.dist-info/WHEEL
release_notes_generator-1.2.1.dist-info/entry_points.txt
release_notes_generator-1.2.1.dist-info/top_level.txt
release_notes_generator-1.2.1.dist-info/RECORD
