Metadata-Version: 2.1
Name: release-notes-generator
Version: 1.2.1
Summary: A Python package that parses a specific PR template given a list of PRs and generates release notes form them.
Home-page: https://github.counsyl.com/lims/release_note_generator
Author: mmentele
Author-email: mmentele@counsyl.com
License: MIT
Keywords: releases notes
Platform: UNKNOWN
Classifier: Development Status :: 4 - Beta
Classifier: Intended Audience :: Developers
Classifier: Topic :: Software Development :: Build Tools
Classifier: License :: OSI Approved :: MIT License
Classifier: Programming Language :: Python :: 2
Classifier: Programming Language :: Python :: 2.7
Requires-Dist: graphqlclient (<=0.2.0)
Requires-Dist: click (<7)
Requires-Dist: pygithub
Provides-Extra: dev
Provides-Extra: test
